Metadata-Version: 2.1
Name: global-alipay-sdk-python
Version: 1.0.1
Summary: The global alipay gateway SDK for Python.
Home-page: https://github.com/alipay/global-open-sdk-python
Author: songlin.xiesl
Author-email: songlin.xiesl@alibaba-inc.com
License: MIT
Keywords: global,alipay,sdk
Platform: any
Classifier: Intended Audience :: Developers
Classifier: License :: OSI Approved :: MIT License
Classifier: Programming Language :: Python
Classifier: Programming Language :: Python :: 2.7
Classifier: Programming Language :: Python :: 3.2
Classifier: Programming Language :: Python :: 3.3
Classifier: Programming Language :: Python :: 3.4
Classifier: Programming Language :: Python :: 3.5
Classifier: Programming Language :: Python :: 3.6
Classifier: Programming Language :: Python :: 3.7
Classifier: Programming Language :: Python :: 3.8
Classifier: Programming Language :: Python :: 3.9
Classifier: Programming Language :: Python :: 3.10
Classifier: Programming Language :: Python :: 3.11
Classifier: Programming Language :: Python :: 3.12
Classifier: Topic :: Software Development
License-File: LICENSE
Requires-Dist: enum34
Requires-Dist: pytz
Requires-Dist: pycryptodome
Requires-Dist: rsa
